fastapi_authlib/__init__.py
fastapi_authlib/alembic/alembic.ini
fastapi_authlib/alembic/env.py
fastapi_authlib/alembic/README
fastapi_authlib/alembic/script.py.mako
fastapi_authlib/alembic/versions/a55b1fb4f129_init_database.py
fastapi_authlib/config/__init__.py
fastapi_authlib/config/settings.yml
fastapi_authlib/messages/__init__.py
fastapi_authlib/messages/base.py
fastapi_authlib/messages/user.py
fastapi_authlib/models.py
fastapi_authlib/oidc.py
fastapi_authlib/repository/__init__.py
fastapi_authlib/repository/base.py
fastapi_authlib/repository/group.py
fastapi_authlib/repository/group_user_map.py
fastapi_authlib/repository/session.py
fastapi_authlib/repository/user.py
fastapi_authlib/rest_api/__init__.py
fastapi_authlib/rest_api/handler/__init__.py
fastapi_authlib/rest_api/handler/exception_handlers.py
fastapi_authlib/rest_api/routers/__init__.py
fastapi_authlib/rest_api/routers/login.py
fastapi_authlib/rest_api/routers/logout.py
fastapi_authlib/rest_api/routers/user.py
fastapi_authlib/schemas/__init__.py
fastapi_authlib/schemas/base.py
fastapi_authlib/schemas/group.py
fastapi_authlib/schemas/group_user_map.py
fastapi_authlib/schemas/session.py
fastapi_authlib/schemas/user.py
fastapi_authlib/services/__init__.py
fastapi_authlib/services/auth.py
fastapi_authlib/services/base.py
fastapi_authlib/utils/__init__.py
fastapi_authlib/utils/auth_dependency.py
fastapi_authlib/utils/exceptions.py
fastapi_authlib/utils/types.py
fastapi_authlib-0.0.3.dist-info/LICENSE
fastapi_authlib-0.0.3.dist-info/METADATA
fastapi_authlib-0.0.3.dist-info/WHEEL
fastapi_authlib-0.0.3.dist-info/RECORD
