Metadata-Version: 2.1
Name: fastapi-authlib
Version: 0.0.3
Summary: A fastapi authlib authentication library
License: MIT
Author: qiang.xie
Author-email: qiang.xie@zncdata.com
Requires-Python: >=3.10,<4.0
Classifier: License :: OSI Approved :: MIT License
Classifier: Operating System :: OS Independent
Classifier: Programming Language :: Python :: 3
Classifier: Programming Language :: Python :: 3.10
Classifier: Programming Language :: Python :: 3.11
Requires-Dist: aiomysql (>=0.1.1,<0.2.0)
Requires-Dist: alembic (>=1.10.3,<2.0.0)
Requires-Dist: authlib (>=1.2.0,<2.0.0)
Requires-Dist: dynaconf (>=3.1.12,<4.0.0)
Requires-Dist: fastapi (>=0.95.0,<0.96.0)
Requires-Dist: fastapi-sa (>=0.1.0,<0.2.0)
Requires-Dist: httpx (>=0.24.0,<0.25.0)
Requires-Dist: inflection (>=0.5.1,<0.6.0)
Requires-Dist: itsdangerous (>=2.1.2,<3.0.0)
Requires-Dist: pyjwt (>=2.8.0,<3.0.0)
Requires-Dist: sqlalchemy (==1.4.46)
Requires-Dist: uvicorn (>=0.21.1,<0.22.0)
